[
  {
    "kind": "youtube#commentThread",
    "etag": "hclZYn_b6c10dVygasPViIcwAPo",
    "id": "UgyboCJBO7lXcuJ43-R4AaABAg",
    "snippet": {
      "channelId": "UCURdPPOThRHq8xI13KSGuyg",
      "videoId": "u70lvJabuAo",
      "topLevelComment": {
        "kind": "youtube#comment",
        "etag": "rxdnpM4EGWzOZeJbK484Q1X1uFs",
        "id": "UgyboCJBO7lXcuJ43-R4AaABAg",
        "snippet": {
          "channelId": "UCURdPPOThRHq8xI13KSGuyg",
          "videoId": "u70lvJabuAo",
          "textDisplay": "Nonton pake infinix note 40, hp sesuai kantong youtubret pemula 😅.",
          "textOriginal": "Nonton pake infinix note 40, hp sesuai kantong youtubret pemula 😅.",
          "authorDisplayName": "@ilhamnyasikin",
          "authorProfileImageUrl": "https://yt3.ggpht.com/G26_ho9eQg3YRe4c4ZfnxPIoit8XaEw2f9SqEUtSgalKP3aeUW5kXC3aOlyFjPyFbj3XtTuS0w=s48-c-k-c0x00ffffff-no-rj",
          "authorChannelUrl": "http://www.youtube.com/@ilhamnyasikin",
          "authorChannelId": { "value": "UCp431iSbD1yd6D0sO3YK_Yg" },
          "canRate": true,
          "viewerRating": "none",
          "likeCount": 0,
          "publishedAt": "2024-11-10T12:43:12Z",
          "updatedAt": "2024-11-10T12:43:12Z"
        }
      },
      "canReply": true,
      "totalReplyCount": 0,
      "isPublic": true
    }
  },
  {
    "kind": "youtube#commentThread",
    "etag": "jvB6jVd3NIsDMbJ8h9RFPZ6bgmw",
    "id": "Ugx9_ANZebMSyREJgm14AaABAg",
    "snippet": {
      "channelId": "UCURdPPOThRHq8xI13KSGuyg",
      "videoId": "u70lvJabuAo",
      "topLevelComment": {
        "kind": "youtube#comment",
        "etag": "KfJtLPXkRswGE-HNPyFnZtJez8M",
        "id": "Ugx9_ANZebMSyREJgm14AaABAg",
        "snippet": {
          "channelId": "UCURdPPOThRHq8xI13KSGuyg",
          "videoId": "u70lvJabuAo",
          "textDisplay": "up date terus bang cara ngedit2 d cameranya  maklum  ni emak2  gk bisa ngotak ngatik hp 😂😂😂",
          "textOriginal": "up date terus bang cara ngedit2 d cameranya  maklum  ni emak2  gk bisa ngotak ngatik hp 😂😂😂",
          "authorDisplayName": "@fatimzuhrok-qu1wz",
          "authorProfileImageUrl": "https://yt3.ggpht.com/ytc/AIdro_kfnPVJK8BPRcQephOxzbzxb4ULfh5wJtVAwtNCrHf7FLiSXkxBl-Ip0NrnNorUBNw1GQ=s48-c-k-c0x00ffffff-no-rj",
          "authorChannelUrl": "http://www.youtube.com/@fatimzuhrok-qu1wz",
          "authorChannelId": { "value": "UCYeRSUTj0iJL_VFJlrVSh9A" },
          "canRate": true,
          "viewerRating": "none",
          "likeCount": 0,
          "publishedAt": "2024-10-15T03:08:20Z",
          "updatedAt": "2024-10-15T03:08:20Z"
        }
      },
      "canReply": true,
      "totalReplyCount": 0,
      "isPublic": true
    }
  },
  {
    "kind": "youtube#commentThread",
    "etag": "JFmI6uGm5Erd9CA93vsniq47eQk",
    "id": "UgyMiNOFdDIwCt6NNE54AaABAg",
    "snippet": {
      "channelId": "UCURdPPOThRHq8xI13KSGuyg",
      "videoId": "u70lvJabuAo",
      "topLevelComment": {
        "kind": "youtube#comment",
        "etag": "zKy4fNJ4jHGtW7SoRfiF-czTNto",
        "id": "UgyMiNOFdDIwCt6NNE54AaABAg",
        "snippet": {
          "channelId": "UCURdPPOThRHq8xI13KSGuyg",
          "videoId": "u70lvJabuAo",
          "textDisplay": "Beli samsung Galaxy s24\nBerasa pake seri A05S😂😂 mirip dari blakang\nHP flagship modelnya sama dgn HP murah😂😂",
          "textOriginal": "Beli samsung Galaxy s24\nBerasa pake seri A05S😂😂 mirip dari blakang\nHP flagship modelnya sama dgn HP murah😂😂",
          "authorDisplayName": "@Idil766",
          "authorProfileImageUrl": "https://yt3.ggpht.com/SJVPdcrmNUybBG9iO33l_qMw8r-b7oDbP4tn_8q5PNqUt45M13Ja4JgvEObbW0Ym8YU1RDI-=s48-c-k-c0x00ffffff-no-rj",
          "authorChannelUrl": "http://www.youtube.com/@Idil766",
          "authorChannelId": { "value": "UC-R103SILWTmoegc0b6BplA" },
          "canRate": true,
          "viewerRating": "none",
          "likeCount": 0,
          "publishedAt": "2024-09-26T00:21:42Z",
          "updatedAt": "2024-09-26T00:21:42Z"
        }
      },
      "canReply": true,
      "totalReplyCount": 2,
      "isPublic": true
    }
  },
  {
    "kind": "youtube#commentThread",
    "etag": "E_O01PNtB-h59TuSPXbu9CrcR70",
    "id": "UgwpUZ8PdnkjOlkllqp4AaABAg",
    "snippet": {
      "channelId": "UCURdPPOThRHq8xI13KSGuyg",
      "videoId": "u70lvJabuAo",
      "topLevelComment": {
        "kind": "youtube#comment",
        "etag": "R7wzGKqeWMSHRbns2s_05TpsXFI",
        "id": "UgwpUZ8PdnkjOlkllqp4AaABAg",
        "snippet": {
          "channelId": "UCURdPPOThRHq8xI13KSGuyg",
          "videoId": "u70lvJabuAo",
          "textDisplay": "Sayang nya knp s24 basic ga ad RAM 12, masa kalah sama a55",
          "textOriginal": "Sayang nya knp s24 basic ga ad RAM 12, masa kalah sama a55",
          "authorDisplayName": "@agusnda1491",
          "authorProfileImageUrl": "https://yt3.ggpht.com/ytc/AIdro_mVTlc-Mb7E6ktpO7e4gJdHDUN-NU4mDCtVPSv1ks0=s48-c-k-c0x00ffffff-no-rj",
          "authorChannelUrl": "http://www.youtube.com/@agusnda1491",
          "authorChannelId": { "value": "UC_zRibZ7TKxUJnnNfZsvzCA" },
          "canRate": true,
          "viewerRating": "none",
          "likeCount": 2,
          "publishedAt": "2024-09-12T00:42:51Z",
          "updatedAt": "2024-09-12T00:42:51Z"
        }
      },
      "canReply": true,
      "totalReplyCount": 0,
      "isPublic": true
    }
  },
  {
    "kind": "youtube#commentThread",
    "etag": "YxJYdYV_XgAtPAK_l8Ax8TbkvhA",
    "id": "Ugwa3BNiXybPIjJJJlx4AaABAg",
    "snippet": {
      "channelId": "UCURdPPOThRHq8xI13KSGuyg",
      "videoId": "u70lvJabuAo",
      "topLevelComment": {
        "kind": "youtube#comment",
        "etag": "pcKp-7Beu_hCb5sdU87l8Ul7jL0",
        "id": "Ugwa3BNiXybPIjJJJlx4AaABAg",
        "snippet": {
          "channelId": "UCURdPPOThRHq8xI13KSGuyg",
          "videoId": "u70lvJabuAo",
          "textDisplay": "Exynos 2400 bagus kh?",
          "textOriginal": "Exynos 2400 bagus kh?",
          "authorDisplayName": "@muhammaddimasyqi8377",
          "authorProfileImageUrl": "https://yt3.ggpht.com/ytc/AIdro_k5_mmB2Phu8J8qkkltSlFoi77-Kkq3gw0CR4kVPs8D1Ao=s48-c-k-c0x00ffffff-no-rj",
          "authorChannelUrl": "http://www.youtube.com/@muhammaddimasyqi8377",
          "authorChannelId": { "value": "UC_CrKqUloPb4AUwRh6HrE2w" },
          "canRate": true,
          "viewerRating": "none",
          "likeCount": 0,
          "publishedAt": "2024-09-11T22:45:30Z",
          "updatedAt": "2024-09-11T22:45:30Z"
        }
      },
      "canReply": true,
      "totalReplyCount": 2,
      "isPublic": true
    }
  },
  {
    "kind": "youtube#commentThread",
    "etag": "3-HzbuSzSh7r7MUB09PUMfs_dxk",
    "id": "UgyF5skAIZ0nNAVl4-Z4AaABAg",
    "snippet": {
      "channelId": "UCURdPPOThRHq8xI13KSGuyg",
      "videoId": "u70lvJabuAo",
      "topLevelComment": {
        "kind": "youtube#comment",
        "etag": "VNUhPhZKXNXDDJBDYfcrAIsXKWQ",
        "id": "UgyF5skAIZ0nNAVl4-Z4AaABAg",
        "snippet": {
          "channelId": "UCURdPPOThRHq8xI13KSGuyg",
          "videoId": "u70lvJabuAo",
          "textDisplay": "PURWOKERTO YA MAS",
          "textOriginal": "PURWOKERTO YA MAS",
          "authorDisplayName": "@vikqitri2594",
          "authorProfileImageUrl": "https://yt3.ggpht.com/ytc/AIdro_nAGXMoH5NpxkxLoimc7jiZHPBLzPJEB7qAzHucO26g=s48-c-k-c0x00ffffff-no-rj",
          "authorChannelUrl": "http://www.youtube.com/@vikqitri2594",
          "authorChannelId": { "value": "UCBYbbXZE1BO8JWumD9aqb_w" },
          "canRate": true,
          "viewerRating": "none",
          "likeCount": 0,
          "publishedAt": "2024-09-08T01:03:18Z",
          "updatedAt": "2024-09-08T01:03:18Z"
        }
      },
      "canReply": true,
      "totalReplyCount": 0,
      "isPublic": true
    }
  },
  {
    "kind": "youtube#commentThread",
    "etag": "VKETgvJQZr9tg2NRQPSaCv9ELFo",
    "id": "UgzJqnOa1Run4X5Z_3p4AaABAg",
    "snippet": {
      "channelId": "UCURdPPOThRHq8xI13KSGuyg",
      "videoId": "u70lvJabuAo",
      "topLevelComment": {
        "kind": "youtube#comment",
        "etag": "YBsvXx__8607aN19Qc9pQSJGOLY",
        "id": "UgzJqnOa1Run4X5Z_3p4AaABAg",
        "snippet": {
          "channelId": "UCURdPPOThRHq8xI13KSGuyg",
          "videoId": "u70lvJabuAo",
          "textDisplay": "Halo bang. Pernah coba ambil gambar kertas putih? Kenapa s24 reguler saya gak bisa ambil gambar kertas putih bersih. Pasti contrastnya kelihatan (kertasnya jadi ada bintik hitam). Padahal sudah full brightness",
          "textOriginal": "Halo bang. Pernah coba ambil gambar kertas putih? Kenapa s24 reguler saya gak bisa ambil gambar kertas putih bersih. Pasti contrastnya kelihatan (kertasnya jadi ada bintik hitam). Padahal sudah full brightness",
          "authorDisplayName": "@dhaniatami3718",
          "authorProfileImageUrl": "https://yt3.ggpht.com/ytc/AIdro_mU-OLuf_t0H0YDjNozHNVe_-7z7pSxf8yLLLLJQU_jkBs=s48-c-k-c0x00ffffff-no-rj",
          "authorChannelUrl": "http://www.youtube.com/@dhaniatami3718",
          "authorChannelId": { "value": "UCpebqHqd6XrCaj_5QIbR24g" },
          "canRate": true,
          "viewerRating": "none",
          "likeCount": 0,
          "publishedAt": "2024-09-07T06:17:07Z",
          "updatedAt": "2024-09-07T06:17:07Z"
        }
      },
      "canReply": true,
      "totalReplyCount": 0,
      "isPublic": true
    }
  },
  {
    "kind": "youtube#commentThread",
    "etag": "xVWPQyxGdO8xgS8aO3rK_AnwcgA",
    "id": "Ugwaz-DmBXU1uXOcWEB4AaABAg",
    "snippet": {
      "channelId": "UCURdPPOThRHq8xI13KSGuyg",
      "videoId": "u70lvJabuAo",
      "topLevelComment": {
        "kind": "youtube#comment",
        "etag": "Z4aHw50X8lmcA1Z373m-6adEZ5c",
        "id": "Ugwaz-DmBXU1uXOcWEB4AaABAg",
        "snippet": {
          "channelId": "UCURdPPOThRHq8xI13KSGuyg",
          "videoId": "u70lvJabuAo",
          "textDisplay": "Yang mau beli Samsung Galaxy S24 saya punya baru, mau jual. RAM 8/256 GB, warna marble grey. Masih baru, dapat hadiah. Silakan harga bisa nego.",
          "textOriginal": "Yang mau beli Samsung Galaxy S24 saya punya baru, mau jual. RAM 8/256 GB, warna marble grey. Masih baru, dapat hadiah. Silakan harga bisa nego.",
          "authorDisplayName": "@GlobadGlabed",
          "authorProfileImageUrl": "https://yt3.ggpht.com/ClywwPJwrRVXgBYN2gx1560kUtFE55dhlZLWBWjEoaYGwOHrzjtT5YgF6VPjRzvyXfNEAALvhw=s48-c-k-c0x00ffffff-no-rj",
          "authorChannelUrl": "http://www.youtube.com/@GlobadGlabed",
          "authorChannelId": { "value": "UCqa0JHw1dIqXX2kmITYtvfQ" },
          "canRate": true,
          "viewerRating": "none",
          "likeCount": 1,
          "publishedAt": "2024-08-30T07:17:17Z",
          "updatedAt": "2024-08-30T07:17:17Z"
        }
      },
      "canReply": true,
      "totalReplyCount": 1,
      "isPublic": true
    }
  },
  {
    "kind": "youtube#commentThread",
    "etag": "i3PDu4rMMuA43POroOgLUAKLRpY",
    "id": "UgzE7nxXJnAZy_jW7DJ4AaABAg",
    "snippet": {
      "channelId": "UCURdPPOThRHq8xI13KSGuyg",
      "videoId": "u70lvJabuAo",
      "topLevelComment": {
        "kind": "youtube#comment",
        "etag": "fFeyS0IzlRNWwHIt-L288AFvb8Q",
        "id": "UgzE7nxXJnAZy_jW7DJ4AaABAg",
        "snippet": {
          "channelId": "UCURdPPOThRHq8xI13KSGuyg",
          "videoId": "u70lvJabuAo",
          "textDisplay": "Saran agar dibuat jg re-review tiap smartphone setelah 1 tahun, kalau 1 bulan masih tetap bagus, kalau 1 tahun baru kelihatan awet / tdk itu smartphone.",
          "textOriginal": "Saran agar dibuat jg re-review tiap smartphone setelah 1 tahun, kalau 1 bulan masih tetap bagus, kalau 1 tahun baru kelihatan awet / tdk itu smartphone.",
          "authorDisplayName": "@Minepixeler24",
          "authorProfileImageUrl": "https://yt3.ggpht.com/SBO-67urL9T0NCF_iuSgDd7fQH7HI-qQ7BngRq7-FeHx-WrE0fcXS78Asql9QA3pbyGXPZhv=s48-c-k-c0x00ffffff-no-rj",
          "authorChannelUrl": "http://www.youtube.com/@Minepixeler24",
          "authorChannelId": { "value": "UCv8VKelX_W7J2DEtD-fyfiA" },
          "canRate": true,
          "viewerRating": "none",
          "likeCount": 4,
          "publishedAt": "2024-08-26T23:23:29Z",
          "updatedAt": "2024-08-26T23:23:29Z"
        }
      },
      "canReply": true,
      "totalReplyCount": 1,
      "isPublic": true
    }
  },
  {
    "kind": "youtube#commentThread",
    "etag": "HvvbzlflNJrVKFDOVmRQ9saOULo",
    "id": "UgxsgPtm_PMGjk0ucph4AaABAg",
    "snippet": {
      "channelId": "UCURdPPOThRHq8xI13KSGuyg",
      "videoId": "u70lvJabuAo",
      "topLevelComment": {
        "kind": "youtube#comment",
        "etag": "yfhfqvGfUzNd73hGQbPAVk5eZ3Y",
        "id": "UgxsgPtm_PMGjk0ucph4AaABAg",
        "snippet": {
          "channelId": "UCURdPPOThRHq8xI13KSGuyg",
          "videoId": "u70lvJabuAo",
          "textDisplay": "Harga 10an saran ambil iphone 12 ke atas aja bro",
          "textOriginal": "Harga 10an saran ambil iphone 12 ke atas aja bro",
          "authorDisplayName": "@ANGGANONIKKI",
          "authorProfileImageUrl": "https://yt3.ggpht.com/AkWl1a_2AcKSvQajc06ahQd_YtXSNUFa54PUnzEiPEExkmJjV5cwedfpmd3Ue1cm35-5VoP0=s48-c-k-c0x00ffffff-no-rj",
          "authorChannelUrl": "http://www.youtube.com/@ANGGANONIKKI",
          "authorChannelId": { "value": "UC7g5YIrF94l07DyLKD_Jw2Q" },
          "canRate": true,
          "viewerRating": "none",
          "likeCount": 0,
          "publishedAt": "2024-08-21T09:40:27Z",
          "updatedAt": "2024-08-21T09:40:27Z"
        }
      },
      "canReply": true,
      "totalReplyCount": 0,
      "isPublic": true
    }
  },
  {
    "kind": "youtube#commentThread",
    "etag": "NTv3Ose41yLZctkKVvKvSnlyrYY",
    "id": "UgyEPm90WlIRGve5BUl4AaABAg",
    "snippet": {
      "channelId": "UCURdPPOThRHq8xI13KSGuyg",
      "videoId": "u70lvJabuAo",
      "topLevelComment": {
        "kind": "youtube#comment",
        "etag": "UrF75fx4UxT_KBohfWOYOMMyQ88",
        "id": "UgyEPm90WlIRGve5BUl4AaABAg",
        "snippet": {
          "channelId": "UCURdPPOThRHq8xI13KSGuyg",
          "videoId": "u70lvJabuAo",
          "textDisplay": "mantan user galaxy yg beralih ke INFINIX NOTE SERIES☺",
          "textOriginal": "mantan user galaxy yg beralih ke INFINIX NOTE SERIES☺",
          "authorDisplayName": "@iwang4414",
          "authorProfileImageUrl": "https://yt3.ggpht.com/ytc/AIdro_lNjN46GDfKal7js6uorwksQAISiSpzAtd-xDqP5MLxc9Q=s48-c-k-c0x00ffffff-no-rj",
          "authorChannelUrl": "http://www.youtube.com/@iwang4414",
          "authorChannelId": { "value": "UC_bWZpEym586HtBK5YRaHCg" },
          "canRate": true,
          "viewerRating": "none",
          "likeCount": 0,
          "publishedAt": "2024-08-18T14:55:29Z",
          "updatedAt": "2024-08-18T14:55:29Z"
        }
      },
      "canReply": true,
      "totalReplyCount": 0,
      "isPublic": true
    }
  },
  {
    "kind": "youtube#commentThread",
    "etag": "CUSM6eOjmRMokGAmRqKA0CuIZFY",
    "id": "UgwLzX_wRK7VV8gKXJN4AaABAg",
    "snippet": {
      "channelId": "UCURdPPOThRHq8xI13KSGuyg",
      "videoId": "u70lvJabuAo",
      "topLevelComment": {
        "kind": "youtube#comment",
        "etag": "3r-Zkx17yruneykfQ04lpzfQqO0",
        "id": "UgwLzX_wRK7VV8gKXJN4AaABAg",
        "snippet": {
          "channelId": "UCURdPPOThRHq8xI13KSGuyg",
          "videoId": "u70lvJabuAo",
          "textDisplay": "perekaman nya kok kayak agak patah patah ya",
          "textOriginal": "perekaman nya kok kayak agak patah patah ya",
          "authorDisplayName": "@tyasyudhistira4092",
          "authorProfileImageUrl": "https://yt3.ggpht.com/ytc/AIdro_nAZ4_wGgDf_NiMRfzOhUL-Ye0vTWnuvR1H5O0zpc0=s48-c-k-c0x00ffffff-no-rj",
          "authorChannelUrl": "http://www.youtube.com/@tyasyudhistira4092",
          "authorChannelId": { "value": "UCp27V6iSc25efMzBX02p5kg" },
          "canRate": true,
          "viewerRating": "none",
          "likeCount": 0,
          "publishedAt": "2024-08-13T03:42:49Z",
          "updatedAt": "2024-08-13T03:42:49Z"
        }
      },
      "canReply": true,
      "totalReplyCount": 0,
      "isPublic": true
    }
  },
  {
    "kind": "youtube#commentThread",
    "etag": "YwCYFpvMwNbFu9zV4Mzn--SFUkQ",
    "id": "UgxEbBSN_8sqld-Nsr14AaABAg",
    "snippet": {
      "channelId": "UCURdPPOThRHq8xI13KSGuyg",
      "videoId": "u70lvJabuAo",
      "topLevelComment": {
        "kind": "youtube#comment",
        "etag": "dg7DeO78QgyLA3FLiA0uihJdkVY",
        "id": "UgxEbBSN_8sqld-Nsr14AaABAg",
        "snippet": {
          "channelId": "UCURdPPOThRHq8xI13KSGuyg",
          "videoId": "u70lvJabuAo",
          "textDisplay": "Izin admin, aku mau tanya kenapa ya s24ku panas mulu klo dipake dan batere boros padahal enggak main game",
          "textOriginal": "Izin admin, aku mau tanya kenapa ya s24ku panas mulu klo dipake dan batere boros padahal enggak main game",
          "authorDisplayName": "@RirinWindarsih",
          "authorProfileImageUrl": "https://yt3.ggpht.com/ytc/AIdro_nMjpdw5OAbqtVVZ4COuk2Bbilff2i5P1mOD0Bs_nx0YQ=s48-c-k-c0x00ffffff-no-rj",
          "authorChannelUrl": "http://www.youtube.com/@RirinWindarsih",
          "authorChannelId": { "value": "UCBbxa_SdLMvyIMwh0Bcnbsw" },
          "canRate": true,
          "viewerRating": "none",
          "likeCount": 0,
          "publishedAt": "2024-08-04T15:20:17Z",
          "updatedAt": "2024-08-04T15:20:17Z"
        }
      },
      "canReply": true,
      "totalReplyCount": 1,
      "isPublic": true
    }
  },
  {
    "kind": "youtube#commentThread",
    "etag": "GzPA8JmoikiHiKEzb9eU0McKrzQ",
    "id": "Ugz0rDSOHPqjT116dzJ4AaABAg",
    "snippet": {
      "channelId": "UCURdPPOThRHq8xI13KSGuyg",
      "videoId": "u70lvJabuAo",
      "topLevelComment": {
        "kind": "youtube#comment",
        "etag": "msnv5sqkLduueeawvdpDfSc2Hao",
        "id": "Ugz0rDSOHPqjT116dzJ4AaABAg",
        "snippet": {
          "channelId": "UCURdPPOThRHq8xI13KSGuyg",
          "videoId": "u70lvJabuAo",
          "textDisplay": "Bukan nya chipset nya sd 8gen3",
          "textOriginal": "Bukan nya chipset nya sd 8gen3",
          "authorDisplayName": "@lovelytirta2214",
          "authorProfileImageUrl": "https://yt3.ggpht.com/ytc/AIdro_mMCFGLpx-oVhpUD-5nWuGkQGaSnhc77pZDhv7mEa7cxk6UAAgzralettYUi9Lid9Cr3w=s48-c-k-c0x00ffffff-no-rj",
          "authorChannelUrl": "http://www.youtube.com/@lovelytirta2214",
          "authorChannelId": { "value": "UCx07SNdBuBNLgJGj_8gV5Pg" },
          "canRate": true,
          "viewerRating": "none",
          "likeCount": 0,
          "publishedAt": "2024-07-22T02:19:11Z",
          "updatedAt": "2024-07-22T02:19:11Z"
        }
      },
      "canReply": true,
      "totalReplyCount": 0,
      "isPublic": true
    }
  },
  {
    "kind": "youtube#commentThread",
    "etag": "p4aeqc5dNQXzJrL5qgV9jvFieZ4",
    "id": "UgwoDkkKgsxg--fhUSJ4AaABAg",
    "snippet": {
      "channelId": "UCURdPPOThRHq8xI13KSGuyg",
      "videoId": "u70lvJabuAo",
      "topLevelComment": {
        "kind": "youtube#comment",
        "etag": "bq9AJ4gTb0yfxxKoXDs696qevsU",
        "id": "UgwoDkkKgsxg--fhUSJ4AaABAg",
        "snippet": {
          "channelId": "UCURdPPOThRHq8xI13KSGuyg",
          "videoId": "u70lvJabuAo",
          "textDisplay": "Tangguh tpi baterainya boros bgt,jadi jarang² di mainin..percuma jg punya ho yg bisa nopang berat tpi ragu mau pake ..... A55 sih worth it bgt baterai Badak",
          "textOriginal": "Tangguh tpi baterainya boros bgt,jadi jarang² di mainin..percuma jg punya ho yg bisa nopang berat tpi ragu mau pake ..... A55 sih worth it bgt baterai Badak",
          "authorDisplayName": "@afadira1910",
          "authorProfileImageUrl": "https://yt3.ggpht.com/6m5v3UxcHpO8eWF9JOjBjh2Gf8NITP7oeSW65S71LzjRYJCVZNFRYDvAEdRc5iOOGUFayIWPPg=s48-c-k-c0x00ffffff-no-rj",
          "authorChannelUrl": "http://www.youtube.com/@afadira1910",
          "authorChannelId": { "value": "UCzywh-LtHxxUoa_P4SML-vw" },
          "canRate": true,
          "viewerRating": "none",
          "likeCount": 0,
          "publishedAt": "2024-07-08T06:53:17Z",
          "updatedAt": "2024-07-08T06:53:17Z"
        }
      },
      "canReply": true,
      "totalReplyCount": 0,
      "isPublic": true
    }
  },
  {
    "kind": "youtube#commentThread",
    "etag": "DbVOwu6NoiqvmKdkv20o9m_hxQE",
    "id": "UgzGZk5l88ywwnvmOJB4AaABAg",
    "snippet": {
      "channelId": "UCURdPPOThRHq8xI13KSGuyg",
      "videoId": "u70lvJabuAo",
      "topLevelComment": {
        "kind": "youtube#comment",
        "etag": "MK0W5mxRejPIdG0F7KtOhCqtZug",
        "id": "UgzGZk5l88ywwnvmOJB4AaABAg",
        "snippet": {
          "channelId": "UCURdPPOThRHq8xI13KSGuyg",
          "videoId": "u70lvJabuAo",
          "textDisplay": "Portrait modenya ga direview, padahal termasuk fitur terbaik dikelasnya",
          "textOriginal": "Portrait modenya ga direview, padahal termasuk fitur terbaik dikelasnya",
          "authorDisplayName": "@PohonCerita",
          "authorProfileImageUrl": "https://yt3.ggpht.com/y7DtePKreO62OugatrvwzJeGI-1sm28FtsTDcNSxeEpFbClC7Ktl_tcmmzovJWuqhqZyF_dT=s48-c-k-c0x00ffffff-no-rj",
          "authorChannelUrl": "http://www.youtube.com/@PohonCerita",
          "authorChannelId": { "value": "UCHrL9XhIqk7LV9Ya6Qa_Hcg" },
          "canRate": true,
          "viewerRating": "none",
          "likeCount": 1,
          "publishedAt": "2024-07-02T12:12:02Z",
          "updatedAt": "2024-07-02T12:12:02Z"
        }
      },
      "canReply": true,
      "totalReplyCount": 0,
      "isPublic": true
    }
  },
  {
    "kind": "youtube#commentThread",
    "etag": "ZwviUb3rTJ0hMET09UtCMTEctLY",
    "id": "UgzQpYGSbH2Ytx2Kjmx4AaABAg",
    "snippet": {
      "channelId": "UCURdPPOThRHq8xI13KSGuyg",
      "videoId": "u70lvJabuAo",
      "topLevelComment": {
        "kind": "youtube#comment",
        "etag": "bant79ErIkhyth0mJZW2ItBoTZo",
        "id": "UgzQpYGSbH2Ytx2Kjmx4AaABAg",
        "snippet": {
          "channelId": "UCURdPPOThRHq8xI13KSGuyg",
          "videoId": "u70lvJabuAo",
          "textDisplay": "S24 plus dah paling asek dr segi batere jg lebih gede drpd yg reguler",
          "textOriginal": "S24 plus dah paling asek dr segi batere jg lebih gede drpd yg reguler",
          "authorDisplayName": "@valentinobotak7715",
          "authorProfileImageUrl": "https://yt3.ggpht.com/ytc/AIdro_nIM94I5mSdYoQZdHwkWpw9FnVvoCLBke553A6HJiU=s48-c-k-c0x00ffffff-no-rj",
          "authorChannelUrl": "http://www.youtube.com/@valentinobotak7715",
          "authorChannelId": { "value": "UCh_rAB7aw9SfoKsvvc7syhw" },
          "canRate": true,
          "viewerRating": "none",
          "likeCount": 0,
          "publishedAt": "2024-06-23T19:52:43Z",
          "updatedAt": "2024-06-23T19:52:43Z"
        }
      },
      "canReply": true,
      "totalReplyCount": 0,
      "isPublic": true
    }
  },
  {
    "kind": "youtube#commentThread",
    "etag": "suwsbP9a0AwC8-GndlKdMMBZF-k",
    "id": "Ugx3OPwCGnALBl2oYqp4AaABAg",
    "snippet": {
      "channelId": "UCURdPPOThRHq8xI13KSGuyg",
      "videoId": "u70lvJabuAo",
      "topLevelComment": {
        "kind": "youtube#comment",
        "etag": "wNO8FoCz4J20Vq9MaG6vjith3-Y",
        "id": "Ugx3OPwCGnALBl2oYqp4AaABAg",
        "snippet": {
          "channelId": "UCURdPPOThRHq8xI13KSGuyg",
          "videoId": "u70lvJabuAo",
          "textDisplay": "p adu sama 11 ku😢",
          "textOriginal": "p adu sama 11 ku😢",
          "authorDisplayName": "@riansyh",
          "authorProfileImageUrl": "https://yt3.ggpht.com/ytc/AIdro_l3eSdJrs9xkcAFM7kExUd2KzasO2x_y1BOcwBOQFRsO4jhq02GQpbHzLNdWF64M9fNlQ=s48-c-k-c0x00ffffff-no-rj",
          "authorChannelUrl": "http://www.youtube.com/@riansyh",
          "authorChannelId": { "value": "UCvncL9Vkh9lWHufDzyHwUxQ" },
          "canRate": true,
          "viewerRating": "none",
          "likeCount": 0,
          "publishedAt": "2024-06-04T14:28:48Z",
          "updatedAt": "2024-06-04T14:28:48Z"
        }
      },
      "canReply": true,
      "totalReplyCount": 0,
      "isPublic": true
    }
  },
  {
    "kind": "youtube#commentThread",
    "etag": "S5U52AqeBxMcyD6mldC9VQ7WMuc",
    "id": "Ugyf7jkPhxeGoLSSvkJ4AaABAg",
    "snippet": {
      "channelId": "UCURdPPOThRHq8xI13KSGuyg",
      "videoId": "u70lvJabuAo",
      "topLevelComment": {
        "kind": "youtube#comment",
        "etag": "whoMbesQslrEy5ubBdUDUNu2jVs",
        "id": "Ugyf7jkPhxeGoLSSvkJ4AaABAg",
        "snippet": {
          "channelId": "UCURdPPOThRHq8xI13KSGuyg",
          "videoId": "u70lvJabuAo",
          "textDisplay": "Gan hpnya suka panas kayak S23 FE ga ??",
          "textOriginal": "Gan hpnya suka panas kayak S23 FE ga ??",
          "authorDisplayName": "@FerrySandi-rq2uu",
          "authorProfileImageUrl": "https://yt3.ggpht.com/l0Cc_dFSwPsPMrbzggQxWIfxHOPXyDqoLo1c6PKIRWS1ecS0Oc_vRc0vPFTkdabGgSOOkNxyF7Y=s48-c-k-c0x00ffffff-no-rj",
          "authorChannelUrl": "http://www.youtube.com/@FerrySandi-rq2uu",
          "authorChannelId": { "value": "UCWkL-uuDMZhJIOJbSPUgu9g" },
          "canRate": true,
          "viewerRating": "none",
          "likeCount": 0,
          "publishedAt": "2024-06-04T05:00:13Z",
          "updatedAt": "2024-06-04T05:00:13Z"
        }
      },
      "canReply": true,
      "totalReplyCount": 0,
      "isPublic": true
    }
  },
  {
    "kind": "youtube#commentThread",
    "etag": "GPNBnxJqB7sDgm5WIa3SQ5PWO5o",
    "id": "UgwswYzjXTiBLSW5ybd4AaABAg",
    "snippet": {
      "channelId": "UCURdPPOThRHq8xI13KSGuyg",
      "videoId": "u70lvJabuAo",
      "topLevelComment": {
        "kind": "youtube#comment",
        "etag": "ZkYT7VEdhGtspqRWkmc1Ki1zvb4",
        "id": "UgwswYzjXTiBLSW5ybd4AaABAg",
        "snippet": {
          "channelId": "UCURdPPOThRHq8xI13KSGuyg",
          "videoId": "u70lvJabuAo",
          "textDisplay": "yang bilang desain sama dengan midrange. itu gak bener sih. soalnya keliatan klo lu liat langsung bukan dr video unboxing atau review. contoh s24 reguler yg saya pakai beda dengan a55. cuma letak dan bentuk kamera aja yg sm. ukuran, bazle, frame. materi belakang hp jelas beda",
          "textOriginal": "yang bilang desain sama dengan midrange. itu gak bener sih. soalnya keliatan klo lu liat langsung bukan dr video unboxing atau review. contoh s24 reguler yg saya pakai beda dengan a55. cuma letak dan bentuk kamera aja yg sm. ukuran, bazle, frame. materi belakang hp jelas beda",
          "authorDisplayName": "@guratsisi2551",
          "authorProfileImageUrl": "https://yt3.ggpht.com/1AnzQ_t41mBFyfDy3AMJeQg9cP-CyGWxpHPGpv7gp5Sq0FKNFwso-dy1-Wx4Wcz0iywvPkpT1zk=s48-c-k-c0x00ffffff-no-rj",
          "authorChannelUrl": "http://www.youtube.com/@guratsisi2551",
          "authorChannelId": { "value": "UCD1VF8Dl4mIsVO01CkAy_Tw" },
          "canRate": true,
          "viewerRating": "none",
          "likeCount": 0,
          "publishedAt": "2024-06-03T00:53:43Z",
          "updatedAt": "2024-06-03T00:53:43Z"
        }
      },
      "canReply": true,
      "totalReplyCount": 1,
      "isPublic": true
    }
  }
]
